[
  {
    "index": 0,
    "year": 14,
    "TEAM": "Atlanta Hawks",
    "lasy_year_playoff": "True",
    "GDP": 325003,
    "pop": 5595,
    "SALARY": 52150108,
    "turnover_metrics": 0.16824907011446744,
    "median_ast": 3,
    "offensive_index": 2.3927812488968896,
    "playoff": "True",
    "prediction": 0.08283992877142989
  },
  {
    "index": 1,
    "year": 15,
    "TEAM": "Atlanta Hawks",
    "lasy_year_playoff": "True",
    "GDP": 347745,
    "pop": 5689,
    "SALARY": 52112642,
    "turnover_metrics": 0.16800094152246942,
    "median_ast": 2.95,
    "offensive_index": 2.315522577161135,
    "playoff": "True",
    "prediction": 0.07976344847214606
  },
  {
    "index": 2,
    "year": 16,
    "TEAM": "Atlanta Hawks",
    "lasy_year_playoff": "True",
    "GDP": 369996,
    "pop": 5792,
    "SALARY": 68126061,
    "turnover_metrics": 0.17293571569032953,
    "median_ast": 3.25,
    "offensive_index": 1.4647026613769731,
    "playoff": "True",
    "prediction": 0.03453635370803075
  },
  {
    "index": 3,
    "year": 17,
    "TEAM": "Atlanta Hawks",
    "lasy_year_playoff": "True",
    "GDP": 389472,
    "pop": 5877,
    "SALARY": 88612062,
    "turnover_metrics": 0.16727635777714858,
    "median_ast": 2.3499999999999996,
    "offensive_index": 1.6542658730158724,
    "playoff": "True",
    "prediction": 0.33269374006658337
  },
  {
    "index": 4,
    "year": 18,
    "TEAM": "Atlanta Hawks",
    "lasy_year_playoff": "True",
    "GDP": 411660,
    "pop": 5951,
    "SALARY": 69224606,
    "turnover_metrics": 0.17680576639241966,
    "median_ast": 3.05,
    "offensive_index": 1.4739527389903335,
    "playoff": "False",
    "prediction": 0.0403982020511906
  },
  {
    "index": 5,
    "year": 19,
    "TEAM": "Atlanta Hawks",
    "lasy_year_playoff": "False",
    "GDP": 438937,
    "pop": 6027,
    "SALARY": 58723895,
    "turnover_metrics": 0.18050797054012846,
    "median_ast": 2.4,
    "offensive_index": 2.262118693404598,
    "playoff": "False",
    "prediction": 0.008661696500882679
  },
  {
    "index": 6,
    "year": 20,
    "TEAM": "Atlanta Hawks",
    "lasy_year_playoff": "False",
    "GDP": 425444,
    "pop": 6088,
    "SALARY": 59527671,
    "turnover_metrics": 0.17392748460675758,
    "median_ast": 1.8,
    "offensive_index": 1.2384426543920204,
    "playoff": "False",
    "prediction": 0.0023735086934583535
  },
  {
    "index": 7,
    "year": 21,
    "TEAM": "Atlanta Hawks",
    "lasy_year_playoff": "False",
    "GDP": 449694,
    "pop": 6144,
    "SALARY": 102711011,
    "turnover_metrics": 0.1296192804350977,
    "median_ast": 3.3499999999999996,
    "offensive_index": 2.1468909486974312,
    "playoff": "True",
    "prediction": 0.4645437214755373
  },
  {
    "index": 8,
    "year": 14,
    "TEAM": "Boston Celtics",
    "lasy_year_playoff": "True",
    "GDP": 379925,
    "pop": 4749,
    "SALARY": 65715030,
    "turnover_metrics": 0.17099331678194069,
    "median_ast": 2.6,
    "offensive_index": 1.3459221791014402,
    "playoff": "False",
    "prediction": 0.037243872264890086
  },
  {
    "index": 9,
    "year": 15,
    "TEAM": "Boston Celtics",
    "lasy_year_playoff": "False",
    "GDP": 403931,
    "pop": 4781,
    "SALARY": 48026312,
    "turnover_metrics": 0.17613337407155485,
    "median_ast": 3.55,
    "offensive_index": 1.8153067406084273,
    "playoff": "True",
    "prediction": 0.0009348100891638888
  },
  {
    "index": 10,
    "year": 16,
    "TEAM": "Boston Celtics",
    "lasy_year_playoff": "True",
    "GDP": 418290,
    "pop": 4812,
    "SALARY": 52647268,
    "turnover_metrics": 0.15332455687201435,
    "median_ast": 2.2,
    "offensive_index": 1.7278982485404502,
    "playoff": "True",
    "prediction": 0.09572563509514816
  },
  {
    "index": 11,
    "year": 17,
    "TEAM": "Boston Celtics",
    "lasy_year_playoff": "True",
    "GDP": 434283,
    "pop": 4845,
    "SALARY": 84099197,
    "turnover_metrics": 0.16220420352681902,
    "median_ast": 2.2,
    "offensive_index": 2.0491363211951437,
    "playoff": "True",
    "prediction": 0.544187151725602
  },
  {
    "index": 12,
    "year": 18,
    "TEAM": "Boston Celtics",
    "lasy_year_playoff": "True",
    "GDP": 462230,
    "pop": 4862,
    "SALARY": 108046311,
    "turnover_metrics": 0.15378524617623096,
    "median_ast": 2.55,
    "offensive_index": 2.032670963122092,
    "playoff": "True",
    "prediction": 0.8857968634046527
  },
  {
    "index": 13,
    "year": 19,
    "TEAM": "Boston Celtics",
    "lasy_year_playoff": "True",
    "GDP": 488174,
    "pop": 4876,
    "SALARY": 120060259,
    "turnover_metrics": 0.13913860211202422,
    "median_ast": 3.7,
    "offensive_index": 2.2885444942448925,
    "playoff": "True",
    "prediction": 0.9685090154762932
  },
  {
    "index": 14,
    "year": 20,
    "TEAM": "Boston Celtics",
    "lasy_year_playoff": "True",
    "GDP": 480307,
    "pop": 4878,
    "SALARY": 110472123,
    "turnover_metrics": 0.1552397517984943,
    "median_ast": 2.75,
    "offensive_index": 2.146755135518938,
    "playoff": "True",
    "prediction": 0.9090661621219627
  },
  {
    "index": 15,
    "year": 21,
    "TEAM": "Boston Celtics",
    "lasy_year_playoff": "True",
    "GDP": 507685,
    "pop": 4942,
    "SALARY": 119704126,
    "turnover_metrics": 0.14609375455283724,
    "median_ast": 3.4,
    "offensive_index": 1.8105838223526267,
    "playoff": "True",
    "prediction": 0.9165835938961284
  },
  {
    "index": 16,
    "year": 14,
    "TEAM": "Brooklyn Nets",
    "lasy_year_playoff": "False",
    "GDP": 1507783,
    "pop": 19282,
    "SALARY": 103856790,
    "turnover_metrics": 0.15559654123904762,
    "median_ast": 2.2,
    "offensive_index": 1.4523925112422034,
    "playoff": "True",
    "prediction": 0.8345097488862875
  },
  {
    "index": 17,
    "year": 15,
    "TEAM": "Brooklyn Nets",
    "lasy_year_playoff": "True",
    "GDP": 1570333,
    "pop": 19322,
    "SALARY": 87228441,
    "turnover_metrics": 0.15991768500488293,
    "median_ast": 1.95,
    "offensive_index": 1.0371105595480408,
    "playoff": "True",
    "prediction": 0.9232242135568977
  },
  {
    "index": 18,
    "year": 16,
    "TEAM": "Brooklyn Nets",
    "lasy_year_playoff": "True",
    "GDP": 1638129,
    "pop": 19336,
    "SALARY": 49088922,
    "turnover_metrics": 0.18842086727374777,
    "median_ast": 2.95,
    "offensive_index": 0.9840565649051884,
    "playoff": "False",
    "prediction": 0.12492941256197909
  },
  {
    "index": 19,
    "year": 17,
    "TEAM": "Brooklyn Nets",
    "lasy_year_playoff": "False",
    "GDP": 1690245,
    "pop": 19325,
    "SALARY": 68459173,
    "turnover_metrics": 0.20896846426960436,
    "median_ast": 2.45,
    "offensive_index": 1.5169613678804836,
    "playoff": "False",
    "prediction": 0.05983807949402054
  },
  {
    "index": 20,
    "year": 18,
    "TEAM": "Brooklyn Nets",
    "lasy_year_playoff": "False",
    "GDP": 1790858,
    "pop": 19289,
    "SALARY": 81160405,
    "turnover_metrics": 0.15053368190160643,
    "median_ast": 3.25,
    "offensive_index": 1.9504117436448265,
    "playoff": "False",
    "prediction": 0.8099402497975547
  },
  {
    "index": 21,
    "year": 19,
    "TEAM": "Brooklyn Nets",
    "lasy_year_playoff": "False",
    "GDP": 1872166,
    "pop": 19232,
    "SALARY": 74678930,
    "turnover_metrics": 0.1687728447892724,
    "median_ast": 2.5,
    "offensive_index": 2.041358920943543,
    "playoff": "True",
    "prediction": 0.7368274096772266
  },
  {
    "index": 22,
    "year": 20,
    "TEAM": "Brooklyn Nets",
    "lasy_year_playoff": "True",
    "GDP": 1809323,
    "pop": 20096,
    "SALARY": 82178659,
    "turnover_metrics": 0.16261673197992116,
    "median_ast": 3,
    "offensive_index": 1.9869661875964046,
    "playoff": "True",
    "prediction": 0.9810445689813119
  },
  {
    "index": 23,
    "year": 21,
    "TEAM": "Brooklyn Nets",
    "lasy_year_playoff": "True",
    "GDP": 1912455,
    "pop": 19768,
    "SALARY": 180381490,
    "turnover_metrics": 0.13930334592922622,
    "median_ast": 4.7,
    "offensive_index": 2.948799735485019,
    "playoff": "True",
    "prediction": 0.9999974829535175
  },
  {
    "index": 24,
    "year": 15,
    "TEAM": "Charlotte Hornets",
    "lasy_year_playoff": "True",
    "GDP": 149619,
    "pop": 2450,
    "SALARY": 58390083,
    "turnover_metrics": 0.14353178111400086,
    "median_ast": 2.45,
    "offensive_index": 0.7749414973898834,
    "playoff": "False",
    "prediction": 0.013935858609938973
  },
  {
    "index": 25,
    "year": 16,
    "TEAM": "Charlotte Hornets",
    "lasy_year_playoff": "False",
    "GDP": 157078,
    "pop": 2502,
    "SALARY": 73592820,
    "turnover_metrics": 0.1396104987309448,
    "median_ast": 1.7999999999999998,
    "offensive_index": 1.505450769785632,
    "playoff": "True",
    "prediction": 0.02010955778421192
  },
  {
    "index": 26,
    "year": 17,
    "TEAM": "Charlotte Hornets",
    "lasy_year_playoff": "True",
    "GDP": 168759,
    "pop": 2553,
    "SALARY": 97512840,
    "turnover_metrics": 0.11355217212147718,
    "median_ast": 2.1,
    "offensive_index": 1.7754435107376283,
    "playoff": "False",
    "prediction": 0.8818591990514243
  },
  {
    "index": 27,
    "year": 18,
    "TEAM": "Charlotte Hornets",
    "lasy_year_playoff": "False",
    "GDP": 175993,
    "pop": 2596,
    "SALARY": 117699009,
    "turnover_metrics": 0.134803980634089,
    "median_ast": 1.9000000000000001,
    "offensive_index": 2.217776584317938,
    "playoff": "False",
    "prediction": 0.6772870470900432
  },
  {
    "index": 28,
    "year": 19,
    "TEAM": "Charlotte Hornets",
    "lasy_year_playoff": "False",
    "GDP": 184483,
    "pop": 2640,
    "SALARY": 113179284,
    "turnover_metrics": 0.13603145629738075,
    "median_ast": 2.9000000000000004,
    "offensive_index": 1.5412817653206519,
    "playoff": "False",
    "prediction": 0.18098579205575302
  },
  {
    "index": 29,
    "year": 20,
    "TEAM": "Charlotte Hornets",
    "lasy_year_playoff": "False",
    "GDP": 184819,
    "pop": 2684,
    "SALARY": 65572449,
    "turnover_metrics": 0.1551010203491747,
    "median_ast": 2.05,
    "offensive_index": 0.9991038039974214,
    "playoff": "False",
    "prediction": 0.0020430077325768003
  },
  {
    "index": 30,
    "year": 21,
    "TEAM": "Charlotte Hornets",
    "lasy_year_playoff": "False",
    "GDP": 195353,
    "pop": 2725,
    "SALARY": 91227278,
    "turnover_metrics": 0.1862812000773517,
    "median_ast": 3.5,
    "offensive_index": 1.996894338490264,
    "playoff": "False",
    "prediction": 0.008429070075112595
  },
  {
    "index": 31,
    "year": 14,
    "TEAM": "Chicago Bulls",
    "lasy_year_playoff": "True",
    "GDP": 609478,
    "pop": 9560,
    "SALARY": 62881116,
    "turnover_metrics": 0.16774316148551327,
    "median_ast": 3.4,
    "offensive_index": 1.7845987517814141,
    "playoff": "True",
    "prediction": 0.10919715171700077
  },
  {
    "index": 32,
    "year": 15,
    "TEAM": "Chicago Bulls",
    "lasy_year_playoff": "True",
    "GDP": 636939,
    "pop": 9552,
    "SALARY": 63813219,
    "turnover_metrics": 0.16483719505465583,
    "median_ast": 2.95,
    "offensive_index": 1.9649269928966058,
    "playoff": "True",
    "prediction": 0.2310712527773598
  },
  {
    "index": 33,
    "year": 16,
    "TEAM": "Chicago Bulls",
    "lasy_year_playoff": "True",
    "GDP": 647456,
    "pop": 9534,
    "SALARY": 82059369,
    "turnover_metrics": 0.14574541675309843,
    "median_ast": 3.2,
    "offensive_index": 1.91932888893898,
    "playoff": "False",
    "prediction": 0.6723359287806298
  },
  {
    "index": 34,
    "year": 17,
    "TEAM": "Chicago Bulls",
    "lasy_year_playoff": "False",
    "GDP": 667153,
    "pop": 9514,
    "SALARY": 86339834,
    "turnover_metrics": 0.1475967806178679,
    "median_ast": 2.2,
    "offensive_index": 1.7879405929038275,
    "playoff": "True",
    "prediction": 0.20619601867045423
  },
  {
    "index": 35,
    "year": 18,
    "TEAM": "Chicago Bulls",
    "lasy_year_playoff": "True",
    "GDP": 701955,
    "pop": 9485,
    "SALARY": 60215739,
    "turnover_metrics": 0.15410768696757463,
    "median_ast": 3.4000000000000004,
    "offensive_index": 1.700232724668816,
    "playoff": "False",
    "prediction": 0.1747188375372208
  },
  {
    "index": 36,
    "year": 19,
    "TEAM": "Chicago Bulls",
    "lasy_year_playoff": "False",
    "GDP": 721907,
    "pop": 9454,
    "SALARY": 86889385,
    "turnover_metrics": 0.15575736227095133,
    "median_ast": 3,
    "offensive_index": 0.907462351563103,
    "playoff": "False",
    "prediction": 0.023845598962448148
  },
  {
    "index": 37,
    "year": 20,
    "TEAM": "Chicago Bulls",
    "lasy_year_playoff": "False",
    "GDP": 692988,
    "pop": 9407,
    "SALARY": 61355527,
    "turnover_metrics": 0.17176699340384924,
    "median_ast": 2.7,
    "offensive_index": 0.9799237731475801,
    "playoff": "False",
    "prediction": 0.0025576193909059223
  },
  {
    "index": 38,
    "year": 21,
    "TEAM": "Chicago Bulls",
    "lasy_year_playoff": "False",
    "GDP": 732489,
    "pop": 9479,
    "SALARY": 110667468,
    "turnover_metrics": 0.1615581878119079,
    "median_ast": 4.05,
    "offensive_index": 2.2577603472037,
    "playoff": "False",
    "prediction": 0.4181184180898362
  },
  {
    "index": 39,
    "year": 14,
    "TEAM": "Cleveland Cavaliers",
    "lasy_year_playoff": "False",
    "GDP": 112901,
    "pop": 2068,
    "SALARY": 60474124,
    "turnover_metrics": 0.16584095329289947,
    "median_ast": 2.95,
    "offensive_index": 1.9575225691957043,
    "playoff": "False",
    "prediction": 0.0025974342722601814
  },
  {
    "index": 40,
    "year": 15,
    "TEAM": "Cleveland Cavaliers",
    "lasy_year_playoff": "False",
    "GDP": 113216,
    "pop": 2065,
    "SALARY": 77005321,
    "turnover_metrics": 0.16257737493000055,
    "median_ast": 2.5,
    "offensive_index": 1.9982018236198231,
    "playoff": "True",
    "prediction": 0.01318818507526655
  },
  {
    "index": 41,
    "year": 16,
    "TEAM": "Cleveland Cavaliers",
    "lasy_year_playoff": "True",
    "GDP": 113545,
    "pop": 2061,
    "SALARY": 103835665,
    "turnover_metrics": 0.15323939142912493,
    "median_ast": 2.4,
    "offensive_index": 1.7294113337691317,
    "playoff": "True",
    "prediction": 0.5440528639095145
  },
  {
    "index": 42,
    "year": 17,
    "TEAM": "Cleveland Cavaliers",
    "lasy_year_playoff": "True",
    "GDP": 114578,
    "pop": 2058,
    "SALARY": 124106953,
    "turnover_metrics": 0.16448997958126962,
    "median_ast": 1.85,
    "offensive_index": 2.5824550653594756,
    "playoff": "True",
    "prediction": 0.9542480279665739
  },
  {
    "index": 43,
    "year": 18,
    "TEAM": "Cleveland Cavaliers",
    "lasy_year_playoff": "True",
    "GDP": 117230,
    "pop": 2054,
    "SALARY": 144211463,
    "turnover_metrics": 0.13848362277194018,
    "median_ast": 2.75,
    "offensive_index": 2.190386680988186,
    "playoff": "True",
    "prediction": 0.9868733857242756
  },
  {
    "index": 44,
    "year": 19,
    "TEAM": "Cleveland Cavaliers",
    "lasy_year_playoff": "True",
    "GDP": 119388,
    "pop": 2049,
    "SALARY": 106360394,
    "turnover_metrics": 0.13564687340990136,
    "median_ast": 2.6500000000000004,
    "offensive_index": 0.7930195203725916,
    "playoff": "False",
    "prediction": 0.312443266201426
  },
  {
    "index": 45,
    "year": 20,
    "TEAM": "Cleveland Cavaliers",
    "lasy_year_playoff": "False",
    "GDP": 114298,
    "pop": 2044,
    "SALARY": 121873735,
    "turnover_metrics": 0.1756993010843721,
    "median_ast": 2.85,
    "offensive_index": 1.2649311591541603,
    "playoff": "False",
    "prediction": 0.030415680133213885
  },
  {
    "index": 46,
    "year": 21,
    "TEAM": "Cleveland Cavaliers",
    "lasy_year_playoff": "False",
    "GDP": 120813,
    "pop": 2039,
    "SALARY": 97818789,
    "turnover_metrics": 0.17303250088646566,
    "median_ast": 3.75,
    "offensive_index": 0.5935235507246377,
    "playoff": "False",
    "prediction": 0.0010973314905801336
  },
  {
    "index": 47,
    "year": 14,
    "TEAM": "Dallas Mavericks",
    "lasy_year_playoff": "True",
    "GDP": 417731,
    "pop": 6890,
    "SALARY": 63783748,
    "turnover_metrics": 0.1595223277990339,
    "median_ast": 2.6500000000000004,
    "offensive_index": 2.795833341985175,
    "playoff": "True",
    "prediction": 0.5248758057145725
  },
  {
    "index": 48,
    "year": 15,
    "TEAM": "Dallas Mavericks",
    "lasy_year_playoff": "True",
    "GDP": 438084,
    "pop": 7042,
    "SALARY": 69307539,
    "turnover_metrics": 0.15809834131946626,
    "median_ast": 3.3499999999999996,
    "offensive_index": 1.896022168681372,
    "playoff": "True",
    "prediction": 0.1745848363631354
  },
  {
    "index": 49,
    "year": 16,
    "TEAM": "Dallas Mavericks",
    "lasy_year_playoff": "True",
    "GDP": 456713,
    "pop": 7195,
    "SALARY": 66509738,
    "turnover_metrics": 0.1590095452828622,
    "median_ast": 2.3499999999999996,
    "offensive_index": 1.189721727565764,
    "playoff": "True",
    "prediction": 0.07627786081125618
  },
  {
    "index": 50,
    "year": 17,
    "TEAM": "Dallas Mavericks",
    "lasy_year_playoff": "True",
    "GDP": 480906,
    "pop": 7338,
    "SALARY": 90135356,
    "turnover_metrics": 0.12744427795521046,
    "median_ast": 2.8,
    "offensive_index": 0.6307773109243695,
    "playoff": "False",
    "prediction": 0.3318956933507979
  },
  {
    "index": 51,
    "year": 18,
    "TEAM": "Dallas Mavericks",
    "lasy_year_playoff": "False",
    "GDP": 511963,
    "pop": 7458,
    "SALARY": 72652690,
    "turnover_metrics": 0.12954707128891269,
    "median_ast": 2.3,
    "offensive_index": 1.2181346222699605,
    "playoff": "False",
    "prediction": 0.041302873730093545
  },
  {
    "index": 52,
    "year": 19,
    "TEAM": "Dallas Mavericks",
    "lasy_year_playoff": "False",
    "GDP": 540634,
    "pop": 7574,
    "SALARY": 64017094,
    "turnover_metrics": 0.1529424860119462,
    "median_ast": 2.95,
    "offensive_index": 1.4261866184093315,
    "playoff": "False",
    "prediction": 0.00890816275026369
  },
  {
    "index": 53,
    "year": 20,
    "TEAM": "Dallas Mavericks",
    "lasy_year_playoff": "False",
    "GDP": 534807,
    "pop": 7694,
    "SALARY": 110447596,
    "turnover_metrics": 0.131507317936326,
    "median_ast": 2.9,
    "offensive_index": 2.7570214398224095,
    "playoff": "True",
    "prediction": 0.8863892574959813
  },
  {
    "index": 54,
    "year": 21,
    "TEAM": "Dallas Mavericks",
    "lasy_year_playoff": "True",
    "GDP": 565291,
    "pop": 7760,
    "SALARY": 111979501,
    "turnover_metrics": 0.12402911037227293,
    "median_ast": 1.85,
    "offensive_index": 1.399636347470437,
    "playoff": "True",
    "prediction": 0.9636373119842263
  },
  {
    "index": 55,
    "year": 14,
    "TEAM": "Denver Nuggets",
    "lasy_year_playoff": "True",
    "GDP": 173826,
    "pop": 2755,
    "SALARY": 50769284,
    "turnover_metrics": 0.18655898762682982,
    "median_ast": 2.85,
    "offensive_index": 2.744989995009617,
    "playoff": "False",
    "prediction": 0.04296147626844048
  },
  {
    "index": 56,
    "year": 15,
    "TEAM": "Denver Nuggets",
    "lasy_year_playoff": "False",
    "GDP": 184612,
    "pop": 2814,
    "SALARY": 49581897,
    "turnover_metrics": 0.1667845718113132,
    "median_ast": 2,
    "offensive_index": 1.5477113017350006,
    "playoff": "False",
    "prediction": 0.001192784446473368
  },
  {
    "index": 57,
    "year": 16,
    "TEAM": "Denver Nuggets",
    "lasy_year_playoff": "False",
    "GDP": 190858,
    "pop": 2858,
    "SALARY": 47166727,
    "turnover_metrics": 0.15754914187453187,
    "median_ast": 2.5,
    "offensive_index": 1.3641369684947668,
    "playoff": "False",
    "prediction": 0.0008173684399824063
  },
  {
    "index": 58,
    "year": 17,
    "TEAM": "Denver Nuggets",
    "lasy_year_playoff": "False",
    "GDP": 199940,
    "pop": 2894,
    "SALARY": 69458471,
    "turnover_metrics": 0.15940146534543703,
    "median_ast": 3.45,
    "offensive_index": 2.9537202380952365,
    "playoff": "False",
    "prediction": 0.04193513870204102
  },
  {
    "index": 59,
    "year": 18,
    "TEAM": "Denver Nuggets",
    "lasy_year_playoff": "False",
    "GDP": 213146,
    "pop": 2934,
    "SALARY": 93996095,
    "turnover_metrics": 0.16768951410184965,
    "median_ast": 3.05,
    "offensive_index": 2.600877192982457,
    "playoff": "False",
    "prediction": 0.0974426111864003
  },
  {
    "index": 60,
    "year": 19,
    "TEAM": "Denver Nuggets",
    "lasy_year_playoff": "False",
    "GDP": 227260,
    "pop": 2965,
    "SALARY": 108007022,
    "turnover_metrics": 0.14298662157715328,
    "median_ast": 2.95,
    "offensive_index": 2.272464561019577,
    "playoff": "True",
    "prediction": 0.3399926615296297
  },
  {
    "index": 61,
    "year": 20,
    "TEAM": "Denver Nuggets",
    "lasy_year_playoff": "True",
    "GDP": 223146,
    "pop": 2991,
    "SALARY": 123692097,
    "turnover_metrics": 0.1310952085485608,
    "median_ast": 3,
    "offensive_index": 2.249079483224379,
    "playoff": "True",
    "prediction": 0.9721545322307381
  },
  {
    "index": 62,
    "year": 21,
    "TEAM": "Denver Nuggets",
    "lasy_year_playoff": "True",
    "GDP": 235865,
    "pop": 3036,
    "SALARY": 111180188,
    "turnover_metrics": 0.1492658637583491,
    "median_ast": 3.2,
    "offensive_index": 2.5340758091046505,
    "playoff": "True",
    "prediction": 0.911296316857448
  },
  {
    "index": 63,
    "year": 14,
    "TEAM": "Detroit Pistons",
    "lasy_year_playoff": "False",
    "GDP": 229738,
    "pop": 4311,
    "SALARY": 57230780,
    "turnover_metrics": 0.15578959829754008,
    "median_ast": 2.1500000000000004,
    "offensive_index": 1.8321640195490105,
    "playoff": "False",
    "prediction": 0.006317185515611165
  },
  {
    "index": 64,
    "year": 15,
    "TEAM": "Detroit Pistons",
    "lasy_year_playoff": "False",
    "GDP": 240956,
    "pop": 4310,
    "SALARY": 46033008,
    "turnover_metrics": 0.1580858953955573,
    "median_ast": 3.2,
    "offensive_index": 1.6169591797172485,
    "playoff": "False",
    "prediction": 0.0009598662914884353
  },
  {
    "index": 65,
    "year": 16,
    "TEAM": "Detroit Pistons",
    "lasy_year_playoff": "False",
    "GDP": 248635,
    "pop": 4317,
    "SALARY": 62188855,
    "turnover_metrics": 0.13764146801931804,
    "median_ast": 2.35,
    "offensive_index": 1.367503293535403,
    "playoff": "True",
    "prediction": 0.007774507502291373
  },
  {
    "index": 66,
    "year": 17,
    "TEAM": "Detroit Pistons",
    "lasy_year_playoff": "True",
    "GDP": 253210,
    "pop": 4322,
    "SALARY": 96038428,
    "turnover_metrics": 0.13203423298402478,
    "median_ast": 2.25,
    "offensive_index": 1.3417512838468715,
    "playoff": "False",
    "prediction": 0.6075121424182972
  },
  {
    "index": 67,
    "year": 18,
    "TEAM": "Detroit Pistons",
    "lasy_year_playoff": "False",
    "GDP": 262063,
    "pop": 4324,
    "SALARY": 110575036,
    "turnover_metrics": 0.13810264970919284,
    "median_ast": 3.3,
    "offensive_index": 1.8742391693519513,
    "playoff": "False",
    "prediction": 0.25031759554887995
  },
  {
    "index": 68,
    "year": 19,
    "TEAM": "Detroit Pistons",
    "lasy_year_playoff": "False",
    "GDP": 266608,
    "pop": 4319,
    "SALARY": 110102430,
    "turnover_metrics": 0.12347195883225216,
    "median_ast": 2.15,
    "offensive_index": 1.2940015010275723,
    "playoff": "True",
    "prediction": 0.2938309222097685
  },
  {
    "index": 69,
    "year": 20,
    "TEAM": "Detroit Pistons",
    "lasy_year_playoff": "True",
    "GDP": 254533,
    "pop": 4304,
    "SALARY": 37183021,
    "turnover_metrics": 0.16067149445680728,
    "median_ast": 2.6,
    "offensive_index": 1.5258591843563574,
    "playoff": "False",
    "prediction": 0.008398716631461118
  },
  {
    "index": 70,
    "year": 21,
    "TEAM": "Detroit Pistons",
    "lasy_year_playoff": "False",
    "GDP": 269041,
    "pop": 4315,
    "SALARY": 69863504,
    "turnover_metrics": 0.17161163368099938,
    "median_ast": 3.6,
    "offensive_index": 1.0133099382057442,
    "playoff": "False",
    "prediction": 0.0007040945677730883
  },
  {
    "index": 71,
    "year": 14,
    "TEAM": "Golden State Warriors",
    "lasy_year_playoff": "False",
    "GDP": 412207,
    "pop": 4585,
    "SALARY": 67538533,
    "turnover_metrics": 0.18082467869308266,
    "median_ast": 2.85,
    "offensive_index": 3.129102097967924,
    "playoff": "True",
    "prediction": 0.05376849786337164
  },
  {
    "index": 72,
    "year": 15,
    "TEAM": "Golden State Warriors",
    "lasy_year_playoff": "True",
    "GDP": 443406,
    "pop": 4648,
    "SALARY": 68250595,
    "turnover_metrics": 0.18034788686606967,
    "median_ast": 2.95,
    "offensive_index": 3.666666666666667,
    "playoff": "True",
    "prediction": 0.7222991439926073
  },
  {
    "index": 73,
    "year": 16,
    "TEAM": "Golden State Warriors",
    "lasy_year_playoff": "True",
    "GDP": 472396,
    "pop": 4688,
    "SALARY": 84383983,
    "turnover_metrics": 0.19187125154330253,
    "median_ast": 2.65,
    "offensive_index": 3.675675675675676,
    "playoff": "True",
    "prediction": 0.8604697433573176
  },
  {
    "index": 74,
    "year": 17,
    "TEAM": "Golden State Warriors",
    "lasy_year_playoff": "True",
    "GDP": 519359,
    "pop": 4712,
    "SALARY": 94216298,
    "turnover_metrics": 0.18683182832147519,
    "median_ast": 3,
    "offensive_index": 3.5999999999999988,
    "playoff": "True",
    "prediction": 0.9246195245523483
  },
  {
    "index": 75,
    "year": 18,
    "TEAM": "Golden State Warriors",
    "lasy_year_playoff": "True",
    "GDP": 562046,
    "pop": 4726,
    "SALARY": 131945925,
    "turnover_metrics": 0.18071256220842957,
    "median_ast": 3,
    "offensive_index": 3.4868421052631584,
    "playoff": "True",
    "prediction": 0.9949614928679573
  },
  {
    "index": 76,
    "year": 19,
    "TEAM": "Golden State Warriors",
    "lasy_year_playoff": "True",
    "GDP": 595295,
    "pop": 4724,
    "SALARY": 138294278,
    "turnover_metrics": 0.17002514388471415,
    "median_ast": 3.4000000000000004,
    "offensive_index": 3.485147542593411,
    "playoff": "True",
    "prediction": 0.9976833015473062
  },
  {
    "index": 77,
    "year": 20,
    "TEAM": "Golden State Warriors",
    "lasy_year_playoff": "True",
    "GDP": 588336,
    "pop": 4740,
    "SALARY": 36579380,
    "turnover_metrics": 0.13811231874794763,
    "median_ast": 2.25,
    "offensive_index": 1.1040422267381593,
    "playoff": "False",
    "prediction": 0.03243493959337578
  },
  {
    "index": 78,
    "year": 21,
    "TEAM": "Golden State Warriors",
    "lasy_year_playoff": "False",
    "GDP": 621871,
    "pop": 4623,
    "SALARY": 129635437,
    "turnover_metrics": 0.20984013126619797,
    "median_ast": 2.5999999999999996,
    "offensive_index": 2.3725793544945324,
    "playoff": "False",
    "prediction": 0.3465535115945569
  },
  {
    "index": 79,
    "year": 14,
    "TEAM": "Houston Rockets",
    "lasy_year_playoff": "False",
    "GDP": 441960,
    "pop": 6499,
    "SALARY": 58248544,
    "turnover_metrics": 0.18978327849012178,
    "median_ast": 2.95,
    "offensive_index": 2.808127886687167,
    "playoff": "True",
    "prediction": 0.011572113685790683
  },
  {
    "index": 80,
    "year": 15,
    "TEAM": "Houston Rockets",
    "lasy_year_playoff": "True",
    "GDP": 461490,
    "pop": 6671,
    "SALARY": 66937242,
    "turnover_metrics": 0.1859412935010933,
    "median_ast": 2.55,
    "offensive_index": 1.901391946717623,
    "playoff": "True",
    "prediction": 0.07967768380334042
  },
  {
    "index": 81,
    "year": 16,
    "TEAM": "Houston Rockets",
    "lasy_year_playoff": "True",
    "GDP": 453324,
    "pop": 6806,
    "SALARY": 71234942,
    "turnover_metrics": 0.18598783486116036,
    "median_ast": 1.95,
    "offensive_index": 1.4678354334317638,
    "playoff": "True",
    "prediction": 0.06590110923599156
  },
  {
    "index": 82,
    "year": 17,
    "TEAM": "Houston Rockets",
    "lasy_year_playoff": "True",
    "GDP": 473076,
    "pop": 6899,
    "SALARY": 85427599,
    "turnover_metrics": 0.14642124851118607,
    "median_ast": 2.35,
    "offensive_index": 2.7234418767506994,
    "playoff": "True",
    "prediction": 0.916027487214046
  },
  {
    "index": 83,
    "year": 18,
    "TEAM": "Houston Rockets",
    "lasy_year_playoff": "True",
    "GDP": 505890,
    "pop": 6975,
    "SALARY": 111004826,
    "turnover_metrics": 0.14890485247759333,
    "median_ast": 1.9000000000000001,
    "offensive_index": 2.1073218761188697,
    "playoff": "True",
    "prediction": 0.9611712781271011
  },
  {
    "index": 84,
    "year": 19,
    "TEAM": "Houston Rockets",
    "lasy_year_playoff": "True",
    "GDP": 509312,
    "pop": 7063,
    "SALARY": 117676641,
    "turnover_metrics": 0.13672240642837785,
    "median_ast": 2.05,
    "offensive_index": 1.4419754645119212,
    "playoff": "True",
    "prediction": 0.9458993501635706
  },
  {
    "index": 85,
    "year": 20,
    "TEAM": "Houston Rockets",
    "lasy_year_playoff": "True",
    "GDP": 488165,
    "pop": 7154,
    "SALARY": 137346433,
    "turnover_metrics": 0.1460859156585666,
    "median_ast": 1.55,
    "offensive_index": 1.6098722751348653,
    "playoff": "True",
    "prediction": 0.9872559667881299
  },
  {
    "index": 86,
    "year": 21,
    "TEAM": "Houston Rockets",
    "lasy_year_playoff": "True",
    "GDP": 515990,
    "pop": 7207,
    "SALARY": 108157856,
    "turnover_metrics": 0.17262637728751914,
    "median_ast": 5.1,
    "offensive_index": 0.8800365097359298,
    "playoff": "False",
    "prediction": 0.08813861233017342
  },
  {
    "index": 87,
    "year": 14,
    "TEAM": "Indiana Pacers",
    "lasy_year_playoff": "True",
    "GDP": 125126,
    "pop": 1972,
    "SALARY": 60830218,
    "turnover_metrics": 0.1983111430745444,
    "median_ast": 3,
    "offensive_index": 1.752208192394824,
    "playoff": "True",
    "prediction": 0.005872802793338236
  },
  {
    "index": 88,
    "year": 15,
    "TEAM": "Indiana Pacers",
    "lasy_year_playoff": "True",
    "GDP": 125191,
    "pop": 1987,
    "SALARY": 70424567,
    "turnover_metrics": 0.15975777440170277,
    "median_ast": 3.25,
    "offensive_index": 1.624345047702128,
    "playoff": "False",
    "prediction": 0.04308502297085754
  },
  {
    "index": 89,
    "year": 16,
    "TEAM": "Indiana Pacers",
    "lasy_year_playoff": "False",
    "GDP": 129945,
    "pop": 2008,
    "SALARY": 62580971,
    "turnover_metrics": 0.18502319099252418,
    "median_ast": 2.95,
    "offensive_index": 1.3208268214002163,
    "playoff": "True",
    "prediction": 0.00038164284547447826
  },
  {
    "index": 90,
    "year": 17,
    "TEAM": "Indiana Pacers",
    "lasy_year_playoff": "True",
    "GDP": 133357,
    "pop": 2029,
    "SALARY": 84629666,
    "turnover_metrics": 0.1409890624542839,
    "median_ast": 2.7,
    "offensive_index": 1.9267594537815118,
    "playoff": "True",
    "prediction": 0.4201009035530447
  },
  {
    "index": 91,
    "year": 18,
    "TEAM": "Indiana Pacers",
    "lasy_year_playoff": "True",
    "GDP": 141715,
    "pop": 2053,
    "SALARY": 86066689,
    "turnover_metrics": 0.1545845176040535,
    "median_ast": 2.45,
    "offensive_index": 1.6810776942355883,
    "playoff": "True",
    "prediction": 0.24094642399413865
  },
  {
    "index": 92,
    "year": 19,
    "TEAM": "Indiana Pacers",
    "lasy_year_playoff": "True",
    "GDP": 148367,
    "pop": 2073,
    "SALARY": 93661462,
    "turnover_metrics": 0.15985878283031393,
    "median_ast": 2.7,
    "offensive_index": 1.9364833869915619,
    "playoff": "True",
    "prediction": 0.37669962852746736
  },
  {
    "index": 93,
    "year": 20,
    "TEAM": "Indiana Pacers",
    "lasy_year_playoff": "True",
    "GDP": 146934,
    "pop": 2091,
    "SALARY": 102256648,
    "turnover_metrics": 0.14567902141991748,
    "median_ast": 3.15,
    "offensive_index": 1.9627205804340186,
    "playoff": "True",
    "prediction": 0.6257999542360654
  },
  {
    "index": 94,
    "year": 21,
    "TEAM": "Indiana Pacers",
    "lasy_year_playoff": "True",
    "GDP": 155309,
    "pop": 2109,
    "SALARY": 117214557,
    "turnover_metrics": 0.15457318644635698,
    "median_ast": 4.9,
    "offensive_index": 2.2203856028274207,
    "playoff": "False",
    "prediction": 0.6469505113584614
  },
  {
    "index": 95,
    "year": 14,
    "TEAM": "Los Angeles Clippers",
    "lasy_year_playoff": "False",
    "GDP": 833318,
    "pop": 13160,
    "SALARY": 75020988,
    "turnover_metrics": 0.16413444688220116,
    "median_ast": 2.7,
    "offensive_index": 3.017455403213918,
    "playoff": "True",
    "prediction": 0.4505610158307661
  },
  {
    "index": 96,
    "year": 15,
    "TEAM": "Los Angeles Clippers",
    "lasy_year_playoff": "True",
    "GDP": 882307,
    "pop": 13226,
    "SALARY": 75753649,
    "turnover_metrics": 0.13939638386766726,
    "median_ast": 2.15,
    "offensive_index": 2.617240961519822,
    "playoff": "True",
    "prediction": 0.9666718401933387
  },
  {
    "index": 97,
    "year": 16,
    "TEAM": "Los Angeles Clippers",
    "lasy_year_playoff": "True",
    "GDP": 910277,
    "pop": 13259,
    "SALARY": 91222499,
    "turnover_metrics": 0.14163566360688623,
    "median_ast": 2.05,
    "offensive_index": 1.4323134644235558,
    "playoff": "True",
    "prediction": 0.8981446806837894
  },
  {
    "index": 98,
    "year": 17,
    "TEAM": "Los Angeles Clippers",
    "lasy_year_playoff": "True",
    "GDP": 957632,
    "pop": 13267,
    "SALARY": 108568384,
    "turnover_metrics": 0.15479848978746635,
    "median_ast": 2.5,
    "offensive_index": 2.2361344537815118,
    "playoff": "True",
    "prediction": 0.9850535317051057
  },
  {
    "index": 99,
    "year": 18,
    "TEAM": "Los Angeles Clippers",
    "lasy_year_playoff": "True",
    "GDP": 1006225,
    "pop": 13237,
    "SALARY": 112056712,
    "turnover_metrics": 0.15355014413515677,
    "median_ast": 3.45,
    "offensive_index": 1.8699427139276765,
    "playoff": "False",
    "prediction": 0.9659766098590611
  },
  {
    "index": 100,
    "year": 19,
    "TEAM": "Los Angeles Clippers",
    "lasy_year_playoff": "False",
    "GDP": 1055570,
    "pop": 13182,
    "SALARY": 93267554,
    "turnover_metrics": 0.1494372825215356,
    "median_ast": 2.7,
    "offensive_index": 2.698770419937012,
    "playoff": "True",
    "prediction": 0.8534113381017108
  },
  {
    "index": 101,
    "year": 20,
    "TEAM": "Los Angeles Clippers",
    "lasy_year_playoff": "True",
    "GDP": 1007037,
    "pop": 13110,
    "SALARY": 122699675,
    "turnover_metrics": 0.15453967453926218,
    "median_ast": 3.8,
    "offensive_index": 2.7263088738176267,
    "playoff": "True",
    "prediction": 0.9958360406948169
  },
  {
    "index": 102,
    "year": 21,
    "TEAM": "Los Angeles Clippers",
    "lasy_year_playoff": "True",
    "GDP": 1064438,
    "pop": 13036,
    "SALARY": 131781660,
    "turnover_metrics": 0.14200739675898189,
    "median_ast": 3.25,
    "offensive_index": 2.5159389726149204,
    "playoff": "True",
    "prediction": 0.9988471959349062
  },
  {
    "index": 103,
    "year": 14,
    "TEAM": "Los Angeles Lakers",
    "lasy_year_playoff": "True",
    "GDP": 833318,
    "pop": 13160,
    "SALARY": 71358763,
    "turnover_metrics": 0.1808292753387642,
    "median_ast": 5.25,
    "offensive_index": 2.7871621196044516,
    "playoff": "False",
    "prediction": 0.37402314005622533
  },
  {
    "index": 104,
    "year": 15,
    "TEAM": "Los Angeles Lakers",
    "lasy_year_playoff": "False",
    "GDP": 882307,
    "pop": 13226,
    "SALARY": 56745753,
    "turnover_metrics": 0.1387172854146185,
    "median_ast": 3.65,
    "offensive_index": 1.4058062975117342,
    "playoff": "False",
    "prediction": 0.02118577269743919
  },
  {
    "index": 105,
    "year": 16,
    "TEAM": "Los Angeles Lakers",
    "lasy_year_playoff": "False",
    "GDP": 910277,
    "pop": 13259,
    "SALARY": 67907944,
    "turnover_metrics": 0.15329746197753188,
    "median_ast": 2.45,
    "offensive_index": 0.2432432432432429,
    "playoff": "False",
    "prediction": 0.005589087533066819
  },
  {
    "index": 106,
    "year": 17,
    "TEAM": "Los Angeles Lakers",
    "lasy_year_playoff": "False",
    "GDP": 957632,
    "pop": 13267,
    "SALARY": 81362570,
    "turnover_metrics": 0.15367437661736297,
    "median_ast": 2.45,
    "offensive_index": 1.4832778944911287,
    "playoff": "False",
    "prediction": 0.14984666555637652
  },
  {
    "index": 107,
    "year": 18,
    "TEAM": "Los Angeles Lakers",
    "lasy_year_playoff": "False",
    "GDP": 1006225,
    "pop": 13237,
    "SALARY": 90211740,
    "turnover_metrics": 0.16229521806611716,
    "median_ast": 3.1,
    "offensive_index": 2.132832080200501,
    "playoff": "False",
    "prediction": 0.3737520656442703
  },
  {
    "index": 108,
    "year": 19,
    "TEAM": "Los Angeles Lakers",
    "lasy_year_playoff": "False",
    "GDP": 1055570,
    "pop": 13182,
    "SALARY": 87084310,
    "turnover_metrics": 0.149667610685162,
    "median_ast": 3.05,
    "offensive_index": 1.890049730306027,
    "playoff": "False",
    "prediction": 0.38950136774775923
  },
  {
    "index": 109,
    "year": 20,
    "TEAM": "Los Angeles Lakers",
    "lasy_year_playoff": "False",
    "GDP": 1007037,
    "pop": 13110,
    "SALARY": 99723853,
    "turnover_metrics": 0.17160391770739936,
    "median_ast": 1.75,
    "offensive_index": 2.132255221212937,
    "playoff": "True",
    "prediction": 0.6268339211366746
  },
  {
    "index": 110,
    "year": 21,
    "TEAM": "Los Angeles Lakers",
    "lasy_year_playoff": "True",
    "GDP": 1064438,
    "pop": 13036,
    "SALARY": 124075550,
    "turnover_metrics": 0.18821412027070317,
    "median_ast": 2.8,
    "offensive_index": 1.5267403529830181,
    "playoff": "True",
    "prediction": 0.9220691721558292
  },
  {
    "index": 111,
    "year": 14,
    "TEAM": "Memphis Grizzlies",
    "lasy_year_playoff": "True",
    "GDP": 67512,
    "pop": 1334,
    "SALARY": 67933534,
    "turnover_metrics": 0.13556362074830092,
    "median_ast": 2.75,
    "offensive_index": 1.7065048702950407,
    "playoff": "True",
    "prediction": 0.13099991421867402
  },
  {
    "index": 112,
    "year": 15,
    "TEAM": "Memphis Grizzlies",
    "lasy_year_playoff": "True",
    "GDP": 70561,
    "pop": 1336,
    "SALARY": 70838466,
    "turnover_metrics": 0.1530182160665916,
    "median_ast": 2.35,
    "offensive_index": 1.2827578268876607,
    "playoff": "True",
    "prediction": 0.04460775589556585
  },
  {
    "index": 113,
    "year": 16,
    "TEAM": "Memphis Grizzlies",
    "lasy_year_playoff": "True",
    "GDP": 71984,
    "pop": 1337,
    "SALARY": 75468039,
    "turnover_metrics": 0.14316177767909433,
    "median_ast": 3.05,
    "offensive_index": 0.5454473447592711,
    "playoff": "True",
    "prediction": 0.015711016831899956
  },
  {
    "index": 114,
    "year": 17,
    "TEAM": "Memphis Grizzlies",
    "lasy_year_playoff": "True",
    "GDP": 73510,
    "pop": 1340,
    "SALARY": 103688225,
    "turnover_metrics": 0.15993523804916626,
    "median_ast": 2.05,
    "offensive_index": 1.3266135620915018,
    "playoff": "True",
    "prediction": 0.2992546327774142
  },
  {
    "index": 115,
    "year": 18,
    "TEAM": "Memphis Grizzlies",
    "lasy_year_playoff": "True",
    "GDP": 75275,
    "pop": 1344,
    "SALARY": 96894830,
    "turnover_metrics": 0.17904293300946808,
    "median_ast": 3.8499999999999996,
    "offensive_index": 0.6459899749373443,
    "playoff": "False",
    "prediction": 0.010068313363877368
  },
  {
    "index": 116,
    "year": 19,
    "TEAM": "Memphis Grizzlies",
    "lasy_year_playoff": "False",
    "GDP": 77380,
    "pop": 1346,
    "SALARY": 114634678,
    "turnover_metrics": 0.1489725777692493,
    "median_ast": 3.1,
    "offensive_index": 0.765488991295443,
    "playoff": "False",
    "prediction": 0.018325640139273888
  },
  {
    "index": 117,
    "year": 20,
    "TEAM": "Memphis Grizzlies",
    "lasy_year_playoff": "False",
    "GDP": 77275,
    "pop": 1337,
    "SALARY": 80810703,
    "turnover_metrics": 0.15136451397942524,
    "median_ast": 2.7,
    "offensive_index": 2.346341845603898,
    "playoff": "False",
    "prediction": 0.0424986655636831
  },
  {
    "index": 118,
    "year": 21,
    "TEAM": "Memphis Grizzlies",
    "lasy_year_playoff": "False",
    "GDP": 81679,
    "pop": 1336,
    "SALARY": 88866355,
    "turnover_metrics": 0.12761259920606371,
    "median_ast": 2.85,
    "offensive_index": 2.463619187338846,
    "playoff": "True",
    "prediction": 0.21048662988026529
  },
  {
    "index": 119,
    "year": 14,
    "TEAM": "Miami Heat",
    "lasy_year_playoff": "True",
    "GDP": 288657,
    "pop": 5894,
    "SALARY": 76146557,
    "turnover_metrics": 0.18759962259083435,
    "median_ast": 2.5,
    "offensive_index": 1.7817848266066987,
    "playoff": "True",
    "prediction": 0.06775508664098719
  },
  {
    "index": 120,
    "year": 15,
    "TEAM": "Miami Heat",
    "lasy_year_playoff": "True",
    "GDP": 308287,
    "pop": 5970,
    "SALARY": 74054086,
    "turnover_metrics": 0.17785462159567195,
    "median_ast": 2.95,
    "offensive_index": 0.36719613259668493,
    "playoff": "False",
    "prediction": 0.00513278532711817
  },
  {
    "index": 121,
    "year": 16,
    "TEAM": "Miami Heat",
    "lasy_year_playoff": "False",
    "GDP": 322563,
    "pop": 6055,
    "SALARY": 82106816,
    "turnover_metrics": 0.15911837666078998,
    "median_ast": 3.4,
    "offensive_index": 0.9941009086651291,
    "playoff": "True",
    "prediction": 0.003887386177166629
  },
  {
    "index": 122,
    "year": 17,
    "TEAM": "Miami Heat",
    "lasy_year_playoff": "True",
    "GDP": 340554,
    "pop": 6116,
    "SALARY": 70137651,
    "turnover_metrics": 0.14145600636508632,
    "median_ast": 3.4000000000000004,
    "offensive_index": 1.740085200746965,
    "playoff": "False",
    "prediction": 0.20097543311758653
  },
  {
    "index": 123,
    "year": 18,
    "TEAM": "Miami Heat",
    "lasy_year_playoff": "False",
    "GDP": 360230,
    "pop": 6141,
    "SALARY": 123570000,
    "turnover_metrics": 0.16361059096656777,
    "median_ast": 3.15,
    "offensive_index": 1.582438238453277,
    "playoff": "True",
    "prediction": 0.1821342248482712
  },
  {
    "index": 124,
    "year": 19,
    "TEAM": "Miami Heat",
    "lasy_year_playoff": "True",
    "GDP": 376603,
    "pop": 6165,
    "SALARY": 120021127,
    "turnover_metrics": 0.16984436125067334,
    "median_ast": 3.5,
    "offensive_index": 1.5541667543435105,
    "playoff": "False",
    "prediction": 0.6061414440391872
  },
  {
    "index": 125,
    "year": 20,
    "TEAM": "Miami Heat",
    "lasy_year_playoff": "False",
    "GDP": 365051,
    "pop": 6126,
    "SALARY": 133768080,
    "turnover_metrics": 0.14991278686121867,
    "median_ast": 3.65,
    "offensive_index": 2.627703074374229,
    "playoff": "True",
    "prediction": 0.8268256226766469
  },
  {
    "index": 126,
    "year": 21,
    "TEAM": "Miami Heat",
    "lasy_year_playoff": "True",
    "GDP": 385859,
    "pop": 6092,
    "SALARY": 122522773,
    "turnover_metrics": 0.1762607139641496,
    "median_ast": 3.9000000000000004,
    "offensive_index": 1.3528797679381166,
    "playoff": "True",
    "prediction": 0.42632096412584897
  },
  {
    "index": 127,
    "year": 14,
    "TEAM": "Milwaukee Bucks",
    "lasy_year_playoff": "False",
    "GDP": 87567,
    "pop": 1575,
    "SALARY": 41614796,
    "turnover_metrics": 0.17126360235961474,
    "median_ast": 2.75,
    "offensive_index": 1.4639171804130595,
    "playoff": "False",
    "prediction": 0.0002202224521112429
  },
  {
    "index": 128,
    "year": 15,
    "TEAM": "Milwaukee Bucks",
    "lasy_year_playoff": "False",
    "GDP": 88533,
    "pop": 1577,
    "SALARY": 50441120,
    "turnover_metrics": 0.20878273470833555,
    "median_ast": 2.9,
    "offensive_index": 1.745609707971586,
    "playoff": "True",
    "prediction": 0.00011416039921984554
  },
  {
    "index": 129,
    "year": 16,
    "TEAM": "Milwaukee Bucks",
    "lasy_year_playoff": "True",
    "GDP": 88972,
    "pop": 1577,
    "SALARY": 63265455,
    "turnover_metrics": 0.17493265502615024,
    "median_ast": 3.55,
    "offensive_index": 0.9148766677436404,
    "playoff": "False",
    "prediction": 0.002569415142906422
  },
  {
    "index": 130,
    "year": 17,
    "TEAM": "Milwaukee Bucks",
    "lasy_year_playoff": "False",
    "GDP": 89167,
    "pop": 1575,
    "SALARY": 84626371,
    "turnover_metrics": 0.15913414211875715,
    "median_ast": 3.0999999999999996,
    "offensive_index": 1.6925332633053207,
    "playoff": "True",
    "prediction": 0.009262975981632761
  },
  {
    "index": 131,
    "year": 18,
    "TEAM": "Milwaukee Bucks",
    "lasy_year_playoff": "True",
    "GDP": 91246,
    "pop": 1576,
    "SALARY": 95538607,
    "turnover_metrics": 0.14871773732948929,
    "median_ast": 3.5,
    "offensive_index": 1.269781596849266,
    "playoff": "True",
    "prediction": 0.13967996073680175
  },
  {
    "index": 132,
    "year": 19,
    "TEAM": "Milwaukee Bucks",
    "lasy_year_playoff": "True",
    "GDP": 92618,
    "pop": 1577,
    "SALARY": 118708192,
    "turnover_metrics": 0.13151774015611897,
    "median_ast": 4,
    "offensive_index": 3.015360983102918,
    "playoff": "True",
    "prediction": 0.9745455355591949
  },
  {
    "index": 133,
    "year": 20,
    "TEAM": "Milwaukee Bucks",
    "lasy_year_playoff": "True",
    "GDP": 87950,
    "pop": 1574,
    "SALARY": 113496748,
    "turnover_metrics": 0.15654973957181503,
    "median_ast": 3.1500000000000004,
    "offensive_index": 3.271115409413282,
    "playoff": "True",
    "prediction": 0.9581427353487133
  },
  {
    "index": 134,
    "year": 21,
    "TEAM": "Milwaukee Bucks",
    "lasy_year_playoff": "True",
    "GDP": 92963,
    "pop": 1566,
    "SALARY": 123122306,
    "turnover_metrics": 0.1471198006001604,
    "median_ast": 3.2,
    "offensive_index": 3.33393115942029,
    "playoff": "True",
    "prediction": 0.9870107440706826
  },
  {
    "index": 135,
    "year": 14,
    "TEAM": "Minnesota Timberwolves",
    "lasy_year_playoff": "False",
    "GDP": 232315,
    "pop": 3477,
    "SALARY": 61577648,
    "turnover_metrics": 0.15719668798059072,
    "median_ast": 1.75,
    "offensive_index": 2.9013303764797254,
    "playoff": "False",
    "prediction": 0.07346172772920155
  },
  {
    "index": 136,
    "year": 15,
    "TEAM": "Minnesota Timberwolves",
    "lasy_year_playoff": "False",
    "GDP": 241312,
    "pop": 3505,
    "SALARY": 58905339,
    "turnover_metrics": 0.17494998307909487,
    "median_ast": 2.7,
    "offensive_index": 0.9520946703776013,
    "playoff": "False",
    "prediction": 0.00038981945711209174
  },
  {
    "index": 137,
    "year": 16,
    "TEAM": "Minnesota Timberwolves",
    "lasy_year_playoff": "False",
    "GDP": 247968,
    "pop": 3540,
    "SALARY": 56330841,
    "turnover_metrics": 0.1741724364028296,
    "median_ast": 2.1,
    "offensive_index": 1.0513608374846906,
    "playoff": "False",
    "prediction": 0.000600421080895952
  },
  {
    "index": 138,
    "year": 17,
    "TEAM": "Minnesota Timberwolves",
    "lasy_year_playoff": "False",
    "GDP": 256333,
    "pop": 3578,
    "SALARY": 53728341,
    "turnover_metrics": 0.1716198058804776,
    "median_ast": 2.6500000000000004,
    "offensive_index": 1.6835025676937425,
    "playoff": "False",
    "prediction": 0.0014133947705560384
  },
  {
    "index": 139,
    "year": 18,
    "TEAM": "Minnesota Timberwolves",
    "lasy_year_playoff": "False",
    "GDP": 271255,
    "pop": 3612,
    "SALARY": 98030072,
    "turnover_metrics": 0.14351474387998,
    "median_ast": 2.3499999999999996,
    "offensive_index": 1.7474042248478348,
    "playoff": "True",
    "prediction": 0.13254823172863808
  },
  {
    "index": 140,
    "year": 19,
    "TEAM": "Minnesota Timberwolves",
    "lasy_year_playoff": "True",
    "GDP": 278264,
    "pop": 3640,
    "SALARY": 110238373,
    "turnover_metrics": 0.1272083200582652,
    "median_ast": 3.75,
    "offensive_index": 1.9226339526825607,
    "playoff": "False",
    "prediction": 0.8706558904087439
  },
  {
    "index": 141,
    "year": 20,
    "TEAM": "Minnesota Timberwolves",
    "lasy_year_playoff": "False",
    "GDP": 270282,
    "pop": 3692,
    "SALARY": 31163316,
    "turnover_metrics": 0.18023040585034034,
    "median_ast": 2,
    "offensive_index": 1.5169061201837932,
    "playoff": "False",
    "prediction": 0.0002264168664110766
  },
  {
    "index": 142,
    "year": 21,
    "TEAM": "Minnesota Timberwolves",
    "lasy_year_playoff": "False",
    "GDP": 285688,
    "pop": 3691,
    "SALARY": 122315140,
    "turnover_metrics": 0.15123860838060532,
    "median_ast": 3.3499999999999996,
    "offensive_index": 1.6587586134080199,
    "playoff": "False",
    "prediction": 0.2154305417939755
  },
  {
    "index": 143,
    "year": 14,
    "TEAM": "New Orleans Pelicans",
    "lasy_year_playoff": "False",
    "GDP": 71320,
    "pop": 1250,
    "SALARY": 61769901,
    "turnover_metrics": 0.16179338732170256,
    "median_ast": 2.8,
    "offensive_index": 2.026397808938253,
    "playoff": "False",
    "prediction": 0.0036801632057324144
  },
  {
    "index": 144,
    "year": 15,
    "TEAM": "New Orleans Pelicans",
    "lasy_year_playoff": "False",
    "GDP": 71547,
    "pop": 1261,
    "SALARY": 66707593,
    "turnover_metrics": 0.14754050461010876,
    "median_ast": 3.3499999999999996,
    "offensive_index": 1.8776478489040285,
    "playoff": "True",
    "prediction": 0.005349457872812693
  },
  {
    "index": 145,
    "year": 16,
    "TEAM": "New Orleans Pelicans",
    "lasy_year_playoff": "True",
    "GDP": 71145,
    "pop": 1269,
    "SALARY": 73224871,
    "turnover_metrics": 0.14521322210820725,
    "median_ast": 3.45,
    "offensive_index": 1.3156719062682365,
    "playoff": "False",
    "prediction": 0.0414807960655595
  },
  {
    "index": 146,
    "year": 17,
    "TEAM": "New Orleans Pelicans",
    "lasy_year_playoff": "False",
    "GDP": 79157,
    "pop": 1271,
    "SALARY": 90189893,
    "turnover_metrics": 0.15534798005063302,
    "median_ast": 3.2,
    "offensive_index": 1.713775093370681,
    "playoff": "False",
    "prediction": 0.015144432899147457
  },
  {
    "index": 147,
    "year": 18,
    "TEAM": "New Orleans Pelicans",
    "lasy_year_playoff": "False",
    "GDP": 82669,
    "pop": 1272,
    "SALARY": 109851809,
    "turnover_metrics": 0.16102833309761397,
    "median_ast": 3.55,
    "offensive_index": 2.705782312925171,
    "playoff": "True",
    "prediction": 0.203468261301201
  },
  {
    "index": 148,
    "year": 19,
    "TEAM": "New Orleans Pelicans",
    "lasy_year_playoff": "True",
    "GDP": 83272,
    "pop": 1274,
    "SALARY": 97276096,
    "turnover_metrics": 0.15679146312444248,
    "median_ast": 3.5,
    "offensive_index": 2.537034698987859,
    "playoff": "False",
    "prediction": 0.586710912921611
  },
  {
    "index": 149,
    "year": 20,
    "TEAM": "New Orleans Pelicans",
    "lasy_year_playoff": "False",
    "GDP": 76382,
    "pop": 1270,
    "SALARY": 103704028,
    "turnover_metrics": 0.17758489737570676,
    "median_ast": 2.05,
    "offensive_index": 3.0230836781496624,
    "playoff": "False",
    "prediction": 0.25933339954358714
  },
  {
    "index": 150,
    "year": 21,
    "TEAM": "New Orleans Pelicans",
    "lasy_year_playoff": "False",
    "GDP": 80736,
    "pop": 1262,
    "SALARY": 126398737,
    "turnover_metrics": 0.1663031113525471,
    "median_ast": 3.25,
    "offensive_index": 2.426516904507868,
    "playoff": "False",
    "prediction": 0.3023423247575163
  },
  {
    "index": 151,
    "year": 14,
    "TEAM": "New York Knicks",
    "lasy_year_playoff": "True",
    "GDP": 1507783,
    "pop": 19282,
    "SALARY": 90051718,
    "turnover_metrics": 0.1730505334687676,
    "median_ast": 2.9,
    "offensive_index": 1.5834506869216671,
    "playoff": "False",
    "prediction": 0.9153708540848271
  },
  {
    "index": 152,
    "year": 15,
    "TEAM": "New York Knicks",
    "lasy_year_playoff": "False",
    "GDP": 1570333,
    "pop": 19322,
    "SALARY": 56354381,
    "turnover_metrics": 0.15236438929271348,
    "median_ast": 2.9,
    "offensive_index": 0.7146303258145366,
    "playoff": "False",
    "prediction": 0.04061599643976996
  },
  {
    "index": 153,
    "year": 16,
    "TEAM": "New York Knicks",
    "lasy_year_playoff": "False",
    "GDP": 1638129,
    "pop": 19336,
    "SALARY": 68895850,
    "turnover_metrics": 0.14100321141594566,
    "median_ast": 2.4,
    "offensive_index": 1.017219523526863,
    "playoff": "False",
    "prediction": 0.3329542272482434
  },
  {
    "index": 154,
    "year": 17,
    "TEAM": "New York Knicks",
    "lasy_year_playoff": "False",
    "GDP": 1690245,
    "pop": 19325,
    "SALARY": 93815798,
    "turnover_metrics": 0.1566330080503103,
    "median_ast": 2.25,
    "offensive_index": 1.7859914799253023,
    "playoff": "False",
    "prediction": 0.8838894314114505
  },
  {
    "index": 155,
    "year": 18,
    "TEAM": "New York Knicks",
    "lasy_year_playoff": "False",
    "GDP": 1790858,
    "pop": 19289,
    "SALARY": 96629698,
    "turnover_metrics": 0.1636417689999891,
    "median_ast": 3,
    "offensive_index": 1.6439312567132127,
    "playoff": "False",
    "prediction": 0.8127550211673878
  },
  {
    "index": 156,
    "year": 19,
    "TEAM": "New York Knicks",
    "lasy_year_playoff": "False",
    "GDP": 1872166,
    "pop": 19232,
    "SALARY": 59040791,
    "turnover_metrics": 0.1709172059651815,
    "median_ast": 2.75,
    "offensive_index": 0.7123112317544487,
    "playoff": "False",
    "prediction": 0.05386798412307228
  },
  {
    "index": 157,
    "year": 20,
    "TEAM": "New York Knicks",
    "lasy_year_playoff": "False",
    "GDP": 1809323,
    "pop": 20096,
    "SALARY": 73305346,
    "turnover_metrics": 0.15358016132039504,
    "median_ast": 1.45,
    "offensive_index": 0.9759234140489194,
    "playoff": "False",
    "prediction": 0.5117134886575094
  },
  {
    "index": 158,
    "year": 21,
    "TEAM": "New York Knicks",
    "lasy_year_playoff": "False",
    "GDP": 1912455,
    "pop": 19768,
    "SALARY": 70641985,
    "turnover_metrics": 0.146107631417955,
    "median_ast": 3.1,
    "offensive_index": 1.4948425691295462,
    "playoff": "True",
    "prediction": 0.624611963552881
  },
  {
    "index": 159,
    "year": 14,
    "TEAM": "Oklahoma City Thunder",
    "lasy_year_playoff": "True",
    "GDP": 76575,
    "pop": 1337,
    "SALARY": 66951545,
    "turnover_metrics": 0.15087126950916993,
    "median_ast": 1.5,
    "offensive_index": 2.7539953861455633,
    "playoff": "True",
    "prediction": 0.5357716908383785
  },
  {
    "index": 160,
    "year": 15,
    "TEAM": "Oklahoma City Thunder",
    "lasy_year_playoff": "True",
    "GDP": 73307,
    "pop": 1358,
    "SALARY": 70911310,
    "turnover_metrics": 0.16419633819966112,
    "median_ast": 3.6999999999999997,
    "offensive_index": 2.023113550450712,
    "playoff": "False",
    "prediction": 0.050125349181974296
  },
  {
    "index": 161,
    "year": 16,
    "TEAM": "Oklahoma City Thunder",
    "lasy_year_playoff": "False",
    "GDP": 72301,
    "pop": 1373,
    "SALARY": 87706810,
    "turnover_metrics": 0.1736248198552662,
    "median_ast": 2,
    "offensive_index": 2.5048014549161333,
    "playoff": "True",
    "prediction": 0.04981707074756425
  },
  {
    "index": 162,
    "year": 17,
    "TEAM": "Oklahoma City Thunder",
    "lasy_year_playoff": "True",
    "GDP": 76615,
    "pop": 1382,
    "SALARY": 81834920,
    "turnover_metrics": 0.16039490189673772,
    "median_ast": 1.75,
    "offensive_index": 1.693417366946778,
    "playoff": "True",
    "prediction": 0.1865569340923216
  },
  {
    "index": 163,
    "year": 18,
    "TEAM": "Oklahoma City Thunder",
    "lasy_year_playoff": "True",
    "GDP": 81863,
    "pop": 1394,
    "SALARY": 130962362,
    "turnover_metrics": 0.14965608485835633,
    "median_ast": 1.3,
    "offensive_index": 1.8509667024704626,
    "playoff": "True",
    "prediction": 0.9519552689925787
  },
  {
    "index": 164,
    "year": 19,
    "TEAM": "Oklahoma City Thunder",
    "lasy_year_playoff": "True",
    "GDP": 81388,
    "pop": 1410,
    "SALARY": 130821706,
    "turnover_metrics": 0.1416277468757866,
    "median_ast": 1.6,
    "offensive_index": 2.237807658046279,
    "playoff": "True",
    "prediction": 0.9804041646373146
  },
  {
    "index": 165,
    "year": 20,
    "TEAM": "Oklahoma City Thunder",
    "lasy_year_playoff": "True",
    "GDP": 74398,
    "pop": 1429,
    "SALARY": 125568196,
    "turnover_metrics": 0.1643189463827852,
    "median_ast": 2.0999999999999996,
    "offensive_index": 1.2294353173534427,
    "playoff": "True",
    "prediction": 0.5593713696201884
  },
  {
    "index": 166,
    "year": 21,
    "TEAM": "Oklahoma City Thunder",
    "lasy_year_playoff": "True",
    "GDP": 78639,
    "pop": 1442,
    "SALARY": 57943824,
    "turnover_metrics": 0.1898504963066967,
    "median_ast": 2.9,
    "offensive_index": 0.847315284075754,
    "playoff": "False",
    "prediction": 0.0011278626831577783
  },
  {
    "index": 167,
    "year": 14,
    "TEAM": "Orlando Magic",
    "lasy_year_playoff": "True",
    "GDP": 110831,
    "pop": 2325,
    "SALARY": 31668125,
    "turnover_metrics": 0.1677648669216922,
    "median_ast": 1.9500000000000002,
    "offensive_index": 1.549711478364511,
    "playoff": "False",
    "prediction": 0.0039734336636447504
  },
  {
    "index": 168,
    "year": 15,
    "TEAM": "Orlando Magic",
    "lasy_year_playoff": "False",
    "GDP": 119537,
    "pop": 2390,
    "SALARY": 35762702,
    "turnover_metrics": 0.18767401217517338,
    "median_ast": 2,
    "offensive_index": 0.9991364807045238,
    "playoff": "False",
    "prediction": 0.000049977694931695453
  },
  {
    "index": 169,
    "year": 16,
    "TEAM": "Orlando Magic",
    "lasy_year_playoff": "False",
    "GDP": 126185,
    "pop": 2457,
    "SALARY": 54786490,
    "turnover_metrics": 0.15302208089920272,
    "median_ast": 2.75,
    "offensive_index": 1.4036058577342974,
    "playoff": "False",
    "prediction": 0.0012880456220485874
  },
  {
    "index": 170,
    "year": 17,
    "TEAM": "Orlando Magic",
    "lasy_year_playoff": "False",
    "GDP": 133601,
    "pop": 2520,
    "SALARY": 97801160,
    "turnover_metrics": 0.15453052749508336,
    "median_ast": 2.3,
    "offensive_index": 1.0793271475256756,
    "playoff": "False",
    "prediction": 0.016288892856789076
  },
  {
    "index": 171,
    "year": 18,
    "TEAM": "Orlando Magic",
    "lasy_year_playoff": "False",
    "GDP": 141110,
    "pop": 2576,
    "SALARY": 91051820,
    "turnover_metrics": 0.1756471526195001,
    "median_ast": 3.15,
    "offensive_index": 1.2459720730397434,
    "playoff": "False",
    "prediction": 0.0033414988448811915
  },
  {
    "index": 172,
    "year": 19,
    "TEAM": "Orlando Magic",
    "lasy_year_playoff": "False",
    "GDP": 150158,
    "pop": 2608,
    "SALARY": 85508807,
    "turnover_metrics": 0.14500279392753726,
    "median_ast": 3.35,
    "offensive_index": 1.8071249710666413,
    "playoff": "True",
    "prediction": 0.024616813983361335
  },
  {
    "index": 173,
    "year": 20,
    "TEAM": "Orlando Magic",
    "lasy_year_playoff": "True",
    "GDP": 144096,
    "pop": 2678,
    "SALARY": 118270876,
    "turnover_metrics": 0.13721519364882276,
    "median_ast": 3.4000000000000004,
    "offensive_index": 1.2712469701050353,
    "playoff": "True",
    "prediction": 0.6284409134463557
  },
  {
    "index": 174,
    "year": 21,
    "TEAM": "Orlando Magic",
    "lasy_year_playoff": "True",
    "GDP": 152310,
    "pop": 2692,
    "SALARY": 98312728,
    "turnover_metrics": 0.13439227864870631,
    "median_ast": 3.5999999999999996,
    "offensive_index": 0.7634384169111761,
    "playoff": "False",
    "prediction": 0.14249306577064977
  },
  {
    "index": 175,
    "year": 14,
    "TEAM": "Philadelphia 76ers",
    "lasy_year_playoff": "True",
    "GDP": 394728,
    "pop": 6050,
    "SALARY": 17714407,
    "turnover_metrics": 0.18813356284382776,
    "median_ast": 2.65,
    "offensive_index": 1.4792944803322867,
    "playoff": "False",
    "prediction": 0.0008916383294008628
  },
  {
    "index": 176,
    "year": 15,
    "TEAM": "Philadelphia 76ers",
    "lasy_year_playoff": "False",
    "GDP": 407824,
    "pop": 6060,
    "SALARY": 36200615,
    "turnover_metrics": 0.20265637375307524,
    "median_ast": 3.55,
    "offensive_index": 0.5750110774172994,
    "playoff": "False",
    "prediction": 0.00001176939677024285
  },
  {
    "index": 177,
    "year": 16,
    "TEAM": "Philadelphia 76ers",
    "lasy_year_playoff": "False",
    "GDP": 414884,
    "pop": 6070,
    "SALARY": 26337413,
    "turnover_metrics": 0.1932177784717718,
    "median_ast": 2.45,
    "offensive_index": 0.5490049578352334,
    "playoff": "False",
    "prediction": 0.00001733468488907008
  },
  {
    "index": 178,
    "year": 17,
    "TEAM": "Philadelphia 76ers",
    "lasy_year_playoff": "False",
    "GDP": 418696,
    "pop": 6082,
    "SALARY": 52741524,
    "turnover_metrics": 0.192175482988889,
    "median_ast": 2.3,
    "offensive_index": 1.4235031512605034,
    "playoff": "False",
    "prediction": 0.0006705753805198379
  },
  {
    "index": 179,
    "year": 18,
    "TEAM": "Philadelphia 76ers",
    "lasy_year_playoff": "False",
    "GDP": 435424,
    "pop": 6097,
    "SALARY": 107232296,
    "turnover_metrics": 0.18060536510625574,
    "median_ast": 3.1,
    "offensive_index": 3.1378446115288217,
    "playoff": "True",
    "prediction": 0.4636330544140619
  },
  {
    "index": 180,
    "year": 19,
    "TEAM": "Philadelphia 76ers",
    "lasy_year_playoff": "True",
    "GDP": 450742,
    "pop": 6105,
    "SALARY": 107725529,
    "turnover_metrics": 0.15476647370544405,
    "median_ast": 3.45,
    "offensive_index": 2.804442059634282,
    "playoff": "True",
    "prediction": 0.9499035176514592
  },
  {
    "index": 181,
    "year": 20,
    "TEAM": "Philadelphia 76ers",
    "lasy_year_playoff": "True",
    "GDP": 439055,
    "pop": 6242,
    "SALARY": 120126224,
    "turnover_metrics": 0.1479938316394891,
    "median_ast": 2.95,
    "offensive_index": 2.3962305250185665,
    "playoff": "True",
    "prediction": 0.9730387450797646
  },
  {
    "index": 182,
    "year": 21,
    "TEAM": "Philadelphia 76ers",
    "lasy_year_playoff": "True",
    "GDP": 464081,
    "pop": 6229,
    "SALARY": 141530814,
    "turnover_metrics": 0.1846199077091001,
    "median_ast": 2.75,
    "offensive_index": 2.0191255445896683,
    "playoff": "True",
    "prediction": 0.944743230537922
  },
  {
    "index": 183,
    "year": 14,
    "TEAM": "Phoenix Suns",
    "lasy_year_playoff": "False",
    "GDP": 209291,
    "pop": 4490,
    "SALARY": 30735737,
    "turnover_metrics": 0.17641452182367307,
    "median_ast": 1.75,
    "offensive_index": 2.1895928027746807,
    "playoff": "False",
    "prediction": 0.0009614663483537909
  },
  {
    "index": 184,
    "year": 15,
    "TEAM": "Phoenix Suns",
    "lasy_year_playoff": "False",
    "GDP": 219957,
    "pop": 4580,
    "SALARY": 50864417,
    "turnover_metrics": 0.18133994340854895,
    "median_ast": 3.6500000000000004,
    "offensive_index": 1.408337314280176,
    "playoff": "False",
    "prediction": 0.00022274797693550791
  },
  {
    "index": 185,
    "year": 16,
    "TEAM": "Phoenix Suns",
    "lasy_year_playoff": "False",
    "GDP": 230743,
    "pop": 4675,
    "SALARY": 61171200,
    "turnover_metrics": 0.19564030816008718,
    "median_ast": 2.5,
    "offensive_index": 1.2518696761816022,
    "playoff": "False",
    "prediction": 0.000358120907199512
  },
  {
    "index": 186,
    "year": 17,
    "TEAM": "Phoenix Suns",
    "lasy_year_playoff": "False",
    "GDP": 243103,
    "pop": 4761,
    "SALARY": 69885151,
    "turnover_metrics": 0.1834224133268051,
    "median_ast": 2.15,
    "offensive_index": 1.5150064192343602,
    "playoff": "False",
    "prediction": 0.002432403224082314
  },
  {
    "index": 187,
    "year": 18,
    "TEAM": "Phoenix Suns",
    "lasy_year_playoff": "False",
    "GDP": 259286,
    "pop": 4852,
    "SALARY": 55714030,
    "turnover_metrics": 0.18199889244849163,
    "median_ast": 4.1,
    "offensive_index": 1.0964017185821708,
    "playoff": "False",
    "prediction": 0.00014240069068558963
  },
  {
    "index": 188,
    "year": 19,
    "TEAM": "Phoenix Suns",
    "lasy_year_playoff": "False",
    "GDP": 276914,
    "pop": 4954,
    "SALARY": 64909906,
    "turnover_metrics": 0.15360234223843727,
    "median_ast": 3.05,
    "offensive_index": 0.6825747532773603,
    "playoff": "False",
    "prediction": 0.0008779073543783607
  },
  {
    "index": 189,
    "year": 20,
    "TEAM": "Phoenix Suns",
    "lasy_year_playoff": "False",
    "GDP": 281005,
    "pop": 4868,
    "SALARY": 92763106,
    "turnover_metrics": 0.155259265626822,
    "median_ast": 2,
    "offensive_index": 2.389130083490438,
    "playoff": "False",
    "prediction": 0.22160065595013465
  },
  {
    "index": 190,
    "year": 21,
    "TEAM": "Phoenix Suns",
    "lasy_year_playoff": "False",
    "GDP": 297022,
    "pop": 4946,
    "SALARY": 117239705,
    "turnover_metrics": 0.13519234016971898,
    "median_ast": 2.1,
    "offensive_index": 2.3579127767404637,
    "playoff": "True",
    "prediction": 0.7815473301107074
  },
  {
    "index": 191,
    "year": 14,
    "TEAM": "Portland Trail Blazers",
    "lasy_year_playoff": "False",
    "GDP": 127933,
    "pop": 2345,
    "SALARY": 56549047,
    "turnover_metrics": 0.1584019273768428,
    "median_ast": 2.5,
    "offensive_index": 3.303914993227338,
    "playoff": "True",
    "prediction": 0.049764482983485854
  },
  {
    "index": 192,
    "year": 15,
    "TEAM": "Portland Trail Blazers",
    "lasy_year_playoff": "True",
    "GDP": 137568,
    "pop": 2383,
    "SALARY": 65367301,
    "turnover_metrics": 0.17577692219368246,
    "median_ast": 2.95,
    "offensive_index": 2.2380495437488745,
    "playoff": "True",
    "prediction": 0.05921989179425993
  },
  {
    "index": 193,
    "year": 16,
    "TEAM": "Portland Trail Blazers",
    "lasy_year_playoff": "True",
    "GDP": 145121,
    "pop": 2429,
    "SALARY": 44263743,
    "turnover_metrics": 0.16676106911350608,
    "median_ast": 2.25,
    "offensive_index": 1.862368728194416,
    "playoff": "True",
    "prediction": 0.016554015841661048
  },
  {
    "index": 194,
    "year": 17,
    "TEAM": "Portland Trail Blazers",
    "lasy_year_playoff": "True",
    "GDP": 153173,
    "pop": 2457,
    "SALARY": 99664007,
    "turnover_metrics": 0.1684058106284314,
    "median_ast": 2.55,
    "offensive_index": 2.161542950513539,
    "playoff": "True",
    "prediction": 0.5173153497444332
  },
  {
    "index": 195,
    "year": 18,
    "TEAM": "Portland Trail Blazers",
    "lasy_year_playoff": "True",
    "GDP": 164120,
    "pop": 2475,
    "SALARY": 111021324,
    "turnover_metrics": 0.15427890293638052,
    "median_ast": 1.9,
    "offensive_index": 1.7739885427855355,
    "playoff": "True",
    "prediction": 0.7632929740638439
  },
  {
    "index": 196,
    "year": 19,
    "TEAM": "Portland Trail Blazers",
    "lasy_year_playoff": "True",
    "GDP": 170986,
    "pop": 2492,
    "SALARY": 121003916,
    "turnover_metrics": 0.14950580410124992,
    "median_ast": 2.4,
    "offensive_index": 2.372346021926225,
    "playoff": "True",
    "prediction": 0.9504437708256767
  },
  {
    "index": 197,
    "year": 20,
    "TEAM": "Portland Trail Blazers",
    "lasy_year_playoff": "True",
    "GDP": 168380,
    "pop": 2516,
    "SALARY": 126324546,
    "turnover_metrics": 0.1294661849602242,
    "median_ast": 1.6,
    "offensive_index": 2.061992997576084,
    "playoff": "True",
    "prediction": 0.983891538335281
  },
  {
    "index": 198,
    "year": 21,
    "TEAM": "Portland Trail Blazers",
    "lasy_year_playoff": "True",
    "GDP": 177978,
    "pop": 2512,
    "SALARY": 119927146,
    "turnover_metrics": 0.10802965000211057,
    "median_ast": 1.7999999999999998,
    "offensive_index": 1.857209922646039,
    "playoff": "True",
    "prediction": 0.9847454751997293
  },
  {
    "index": 199,
    "year": 14,
    "TEAM": "Sacramento Kings",
    "lasy_year_playoff": "False",
    "GDP": 113461,
    "pop": 2236,
    "SALARY": 51133379,
    "turnover_metrics": 0.17460288684424344,
    "median_ast": 2.8,
    "offensive_index": 1.525932062966031,
    "playoff": "False",
    "prediction": 0.0004382475260267769
  },
  {
    "index": 200,
    "year": 15,
    "TEAM": "Sacramento Kings",
    "lasy_year_playoff": "False",
    "GDP": 120658,
    "pop": 2263,
    "SALARY": 69920667,
    "turnover_metrics": 0.18460752939769837,
    "median_ast": 3.25,
    "offensive_index": 1.4797693474016533,
    "playoff": "False",
    "prediction": 0.0007178324351249413
  },
  {
    "index": 201,
    "year": 16,
    "TEAM": "Sacramento Kings",
    "lasy_year_playoff": "False",
    "GDP": 124495,
    "pop": 2292,
    "SALARY": 67369469,
    "turnover_metrics": 0.18340163095541817,
    "median_ast": 1.7999999999999998,
    "offensive_index": 1.954387195786278,
    "playoff": "False",
    "prediction": 0.0038486844367817195
  },
  {
    "index": 202,
    "year": 17,
    "TEAM": "Sacramento Kings",
    "lasy_year_playoff": "False",
    "GDP": 130120,
    "pop": 2321,
    "SALARY": 78073084,
    "turnover_metrics": 0.16357406535945435,
    "median_ast": 3.8,
    "offensive_index": 1.6864816760037344,
    "playoff": "False",
    "prediction": 0.0036318678817215126
  },
  {
    "index": 203,
    "year": 18,
    "TEAM": "Sacramento Kings",
    "lasy_year_playoff": "False",
    "GDP": 138347,
    "pop": 2343,
    "SALARY": 62918597,
    "turnover_metrics": 0.1556361127853011,
    "median_ast": 2.3,
    "offensive_index": 1.0783208020050128,
    "playoff": "False",
    "prediction": 0.0014394377302718003
  },
  {
    "index": 204,
    "year": 19,
    "TEAM": "Sacramento Kings",
    "lasy_year_playoff": "False",
    "GDP": 146370,
    "pop": 2364,
    "SALARY": 86661428,
    "turnover_metrics": 0.12625457843798926,
    "median_ast": 2.3,
    "offensive_index": 2.6181813718269744,
    "playoff": "False",
    "prediction": 0.3639391565008644
  },
  {
    "index": 205,
    "year": 20,
    "TEAM": "Sacramento Kings",
    "lasy_year_playoff": "False",
    "GDP": 145412,
    "pop": 2399,
    "SALARY": 101848863,
    "turnover_metrics": 0.1590415159666209,
    "median_ast": 2.9,
    "offensive_index": 1.690119155465236,
    "playoff": "False",
    "prediction": 0.04001011987763098
  },
  {
    "index": 206,
    "year": 21,
    "TEAM": "Sacramento Kings",
    "lasy_year_playoff": "False",
    "GDP": 153700,
    "pop": 2411,
    "SALARY": 88682328,
    "turnover_metrics": 0.14875278869733488,
    "median_ast": 3.55,
    "offensive_index": 1.6369452965235176,
    "playoff": "False",
    "prediction": 0.016637761271065324
  },
  {
    "index": 207,
    "year": 14,
    "TEAM": "San Antonio Spurs",
    "lasy_year_playoff": "True",
    "GDP": 105787,
    "pop": 2329,
    "SALARY": 59159286,
    "turnover_metrics": 0.15822133084427703,
    "median_ast": 2.5,
    "offensive_index": 3.4976278724981467,
    "playoff": "True",
    "prediction": 0.5566181038771258
  },
  {
    "index": 208,
    "year": 15,
    "TEAM": "San Antonio Spurs",
    "lasy_year_playoff": "True",
    "GDP": 112174,
    "pop": 2379,
    "SALARY": 62323360,
    "turnover_metrics": 0.16537914939477658,
    "median_ast": 2.7,
    "offensive_index": 2.3777868358742165,
    "playoff": "True",
    "prediction": 0.1042406866457124
  },
  {
    "index": 209,
    "year": 16,
    "TEAM": "San Antonio Spurs",
    "lasy_year_playoff": "True",
    "GDP": 115263,
    "pop": 2426,
    "SALARY": 81376134,
    "turnover_metrics": 0.15559552473876695,
    "median_ast": 2.6500000000000004,
    "offensive_index": 1.8993264532255354,
    "playoff": "True",
    "prediction": 0.21779392100094117
  },
  {
    "index": 210,
    "year": 17,
    "TEAM": "San Antonio Spurs",
    "lasy_year_playoff": "True",
    "GDP": 117866,
    "pop": 2472,
    "SALARY": 101379068,
    "turnover_metrics": 0.1519482088066291,
    "median_ast": 2.5,
    "offensive_index": 2.5189892623716146,
    "playoff": "True",
    "prediction": 0.8265895444263448
  },
  {
    "index": 211,
    "year": 18,
    "TEAM": "San Antonio Spurs",
    "lasy_year_playoff": "True",
    "GDP": 126384,
    "pop": 2513,
    "SALARY": 107079057,
    "turnover_metrics": 0.16291278365177028,
    "median_ast": 2.8,
    "offensive_index": 1.4967776584317953,
    "playoff": "True",
    "prediction": 0.33571626754724804
  },
  {
    "index": 212,
    "year": 19,
    "TEAM": "San Antonio Spurs",
    "lasy_year_playoff": "True",
    "GDP": 132237,
    "pop": 2550,
    "SALARY": 95125945,
    "turnover_metrics": 0.12951756959040958,
    "median_ast": 2.5,
    "offensive_index": 2.4971277065841813,
    "playoff": "True",
    "prediction": 0.8969174257288115
  },
  {
    "index": 213,
    "year": 20,
    "TEAM": "San Antonio Spurs",
    "lasy_year_playoff": "True",
    "GDP": 132116,
    "pop": 2567,
    "SALARY": 103656241,
    "turnover_metrics": 0.13105803833847934,
    "median_ast": 2.1,
    "offensive_index": 2.5349664977270683,
    "playoff": "False",
    "prediction": 0.9522417638015029
  },
  {
    "index": 214,
    "year": 21,
    "TEAM": "San Antonio Spurs",
    "lasy_year_playoff": "False",
    "GDP": 139647,
    "pop": 2602,
    "SALARY": 96997265,
    "turnover_metrics": 0.1241055625872152,
    "median_ast": 2.15,
    "offensive_index": 1.4812132679825727,
    "playoff": "False",
    "prediction": 0.13334291998880038
  },
  {
    "index": 215,
    "year": 14,
    "TEAM": "Toronto Raptors",
    "lasy_year_playoff": "False",
    "GDP": 317410,
    "pop": 5797,
    "SALARY": 55330242,
    "turnover_metrics": 0.17425683510302598,
    "median_ast": 3.45,
    "offensive_index": 2.1956466698367016,
    "playoff": "True",
    "prediction": 0.0029932653981498115
  },
  {
    "index": 216,
    "year": 15,
    "TEAM": "Toronto Raptors",
    "lasy_year_playoff": "True",
    "GDP": 291375,
    "pop": 5867,
    "SALARY": 65994671,
    "turnover_metrics": 0.14635535309121137,
    "median_ast": 2,
    "offensive_index": 1.4976436256386825,
    "playoff": "True",
    "prediction": 0.15853522937603326
  },
  {
    "index": 217,
    "year": 16,
    "TEAM": "Toronto Raptors",
    "lasy_year_playoff": "True",
    "GDP": 292374,
    "pop": 5938,
    "SALARY": 65347074,
    "turnover_metrics": 0.15193042393453238,
    "median_ast": 1.2,
    "offensive_index": 1.2036891979552524,
    "playoff": "True",
    "prediction": 0.11382364460334794
  },
  {
    "index": 218,
    "year": 17,
    "TEAM": "Toronto Raptors",
    "lasy_year_playoff": "True",
    "GDP": 311658,
    "pop": 6010,
    "SALARY": 106369083,
    "turnover_metrics": 0.13224527399665514,
    "median_ast": 1.65,
    "offensive_index": 1.6499999999999986,
    "playoff": "True",
    "prediction": 0.9106162878473582
  },
  {
    "index": 219,
    "year": 18,
    "TEAM": "Toronto Raptors",
    "lasy_year_playoff": "True",
    "GDP": 324366,
    "pop": 6082,
    "SALARY": 123537375,
    "turnover_metrics": 0.15123532149223143,
    "median_ast": 2.45,
    "offensive_index": 2.341031149301826,
    "playoff": "True",
    "prediction": 0.9714040508501516
  },
  {
    "index": 220,
    "year": 19,
    "TEAM": "Toronto Raptors",
    "lasy_year_playoff": "True",
    "GDP": 332549,
    "pop": 6139,
    "SALARY": 135178786,
    "turnover_metrics": 0.15102995288229837,
    "median_ast": 3.3,
    "offensive_index": 2.4198984351436854,
    "playoff": "True",
    "prediction": 0.9820525182642911
  },
  {
    "index": 221,
    "year": 20,
    "TEAM": "Toronto Raptors",
    "lasy_year_playoff": "True",
    "GDP": 328359,
    "pop": 6197,
    "SALARY": 118082968,
    "turnover_metrics": 0.16619325321578118,
    "median_ast": 2.7,
    "offensive_index": 2.565892400982624,
    "playoff": "True",
    "prediction": 0.9407499407208548
  },
  {
    "index": 222,
    "year": 21,
    "TEAM": "Toronto Raptors",
    "lasy_year_playoff": "True",
    "GDP": 361994,
    "pop": 6255,
    "SALARY": 120783015,
    "turnover_metrics": 0.12227418255942768,
    "median_ast": 2.7,
    "offensive_index": 1.3532748732995468,
    "playoff": "False",
    "prediction": 0.9381101627114351
  },
  {
    "index": 223,
    "year": 14,
    "TEAM": "Utah Jazz",
    "lasy_year_playoff": "True",
    "GDP": 74941,
    "pop": 1152,
    "SALARY": 44412676,
    "turnover_metrics": 0.15464471307990696,
    "median_ast": 2.2,
    "offensive_index": 1.142873685179533,
    "playoff": "False",
    "prediction": 0.005891790765468076
  },
  {
    "index": 224,
    "year": 15,
    "TEAM": "Utah Jazz",
    "lasy_year_playoff": "False",
    "GDP": 79284,
    "pop": 1165,
    "SALARY": 46923029,
    "turnover_metrics": 0.19864116154056816,
    "median_ast": 2.3499999999999996,
    "offensive_index": 1.0857868081806714,
    "playoff": "False",
    "prediction": 0.00005319668748999889
  },
  {
    "index": 225,
    "year": 16,
    "TEAM": "Utah Jazz",
    "lasy_year_playoff": "False",
    "GDP": 84554,
    "pop": 1185,
    "SALARY": 55277867,
    "turnover_metrics": 0.1856193095204221,
    "median_ast": 2.2,
    "offensive_index": 0.7685790461019822,
    "playoff": "False",
    "prediction": 0.00010330006300741191
  },
  {
    "index": 226,
    "year": 17,
    "TEAM": "Utah Jazz",
    "lasy_year_playoff": "False",
    "GDP": 88992,
    "pop": 1205,
    "SALARY": 74141889,
    "turnover_metrics": 0.1777716783090285,
    "median_ast": 2.5,
    "offensive_index": 1.5681343370681609,
    "playoff": "True",
    "prediction": 0.0021483811684758674
  },
  {
    "index": 227,
    "year": 18,
    "TEAM": "Utah Jazz",
    "lasy_year_playoff": "True",
    "GDP": 96992,
    "pop": 1219,
    "SALARY": 97670091,
    "turnover_metrics": 0.1660265161613386,
    "median_ast": 2.45,
    "offensive_index": 1.6783924095954168,
    "playoff": "True",
    "prediction": 0.26136254512265694
  },
  {
    "index": 228,
    "year": 19,
    "TEAM": "Utah Jazz",
    "lasy_year_playoff": "True",
    "GDP": 103150,
    "pop": 1231,
    "SALARY": 104349333,
    "turnover_metrics": 0.1757042039190068,
    "median_ast": 2.55,
    "offensive_index": 2.2697851566609852,
    "playoff": "True",
    "prediction": 0.5196997973524523
  },
  {
    "index": 229,
    "year": 20,
    "TEAM": "Utah Jazz",
    "lasy_year_playoff": "True",
    "GDP": 103913,
    "pop": 1260,
    "SALARY": 111776284,
    "turnover_metrics": 0.17263196203232564,
    "median_ast": 2.3,
    "offensive_index": 2.1243728423475243,
    "playoff": "True",
    "prediction": 0.6461254308609274
  },
  {
    "index": 230,
    "year": 21,
    "TEAM": "Utah Jazz",
    "lasy_year_playoff": "True",
    "GDP": 109836,
    "pop": 1263,
    "SALARY": 128955106,
    "turnover_metrics": 0.1611277638174313,
    "median_ast": 2.5,
    "offensive_index": 2.854672801635992,
    "playoff": "True",
    "prediction": 0.9739349789384343
  },
  {
    "index": 231,
    "year": 14,
    "TEAM": "Washington Wizards",
    "lasy_year_playoff": "False",
    "GDP": 469123,
    "pop": 6036,
    "SALARY": 59773699,
    "turnover_metrics": 0.16876586648156733,
    "median_ast": 2.7,
    "offensive_index": 2.549265181733677,
    "playoff": "True",
    "prediction": 0.024953476362003277
  },
  {
    "index": 232,
    "year": 15,
    "TEAM": "Washington Wizards",
    "lasy_year_playoff": "True",
    "GDP": 488987,
    "pop": 6099,
    "SALARY": 68907892,
    "turnover_metrics": 0.15072603042142355,
    "median_ast": 2.7,
    "offensive_index": 2.1089391295919357,
    "playoff": "True",
    "prediction": 0.4199410582624055
  },
  {
    "index": 233,
    "year": 16,
    "TEAM": "Washington Wizards",
    "lasy_year_playoff": "True",
    "GDP": 508569,
    "pop": 6155,
    "SALARY": 72272440,
    "turnover_metrics": 0.16230309149521877,
    "median_ast": 2,
    "offensive_index": 1.477916406815488,
    "playoff": "False",
    "prediction": 0.2034821395069248
  },
  {
    "index": 234,
    "year": 17,
    "TEAM": "Washington Wizards",
    "lasy_year_playoff": "False",
    "GDP": 525176,
    "pop": 6218,
    "SALARY": 97430036,
    "turnover_metrics": 0.15384304808808189,
    "median_ast": 1.75,
    "offensive_index": 2.322184290382819,
    "playoff": "True",
    "prediction": 0.47684104724051923
  },
  {
    "index": 235,
    "year": 18,
    "TEAM": "Washington Wizards",
    "lasy_year_playoff": "True",
    "GDP": 547123,
    "pop": 6256,
    "SALARY": 123055869,
    "turnover_metrics": 0.16148849879092012,
    "median_ast": 3.05,
    "offensive_index": 2.2657536698890084,
    "playoff": "True",
    "prediction": 0.9597335605882997
  },
  {
    "index": 236,
    "year": 19,
    "TEAM": "Washington Wizards",
    "lasy_year_playoff": "True",
    "GDP": 566892,
    "pop": 6297,
    "SALARY": 115658099,
    "turnover_metrics": 0.150463626477378,
    "median_ast": 3.05,
    "offensive_index": 1.7913747027754985,
    "playoff": "False",
    "prediction": 0.9096703124446132
  },
  {
    "index": 237,
    "year": 20,
    "TEAM": "Washington Wizards",
    "lasy_year_playoff": "False",
    "GDP": 561028,
    "pop": 6386,
    "SALARY": 85196283,
    "turnover_metrics": 0.15951320830467033,
    "median_ast": 3.35,
    "offensive_index": 2.169195618996319,
    "playoff": "False",
    "prediction": 0.08778856396033302
  },
  {
    "index": 238,
    "year": 21,
    "TEAM": "Washington Wizards",
    "lasy_year_playoff": "False",
    "GDP": 593007,
    "pop": 6356,
    "SALARY": 122086882,
    "turnover_metrics": 0.12740341181268744,
    "median_ast": 1.9,
    "offensive_index": 2.192250711300792,
    "playoff": "True",
    "prediction": 0.9355444536726469
  }
]